{
  "players": [
    {
      "id": 1,
      "name": "Iga Swiatek",
      "nationality": "Poland",
      "age": 23,
      "ranking": 1,
      "racquet": "Tecnifibre T-Fight 305",
      "plays": "Right-handed (two-handed backhand)",
      "coach": "Tomasz Wiktorowski",
      "career_titles": 20,
      "grand_slam_titles": 5,
      "career_wins": 278,
      "career_losses": 67,
      "prize_money": "$25,128,902",
      "highest_ranking": 1,
      "year_turned_pro": 2018
    },
    {
      "id": 2,
      "name": "Aryna Sabalenka",
      "nationality": "Belarus",
      "age": 26,
      "ranking": 2,
      "racquet": "Wilson Blade 98",
      "plays": "Right-handed (two-handed backhand)",
      "coach": "Anton Dubrov",
      "career_titles": 14,
      "grand_slam_titles": 3,
      "career_wins": 302,
      "career_losses": 140,
      "prize_money": "$19,587,714",
      "highest_ranking": 2,
      "year_turned_pro": 2015
    },
    {
      "id": 3,
      "name": "Coco Gauff",
      "nationality": "United States",
      "age": 20,
      "ranking": 3,
      "racquet": "Head Boom MP",
      "plays": "Right-handed (two-handed backhand)",
      "coach": "Brad Gilbert",
      "career_titles": 8,
      "grand_slam_titles": 1,
      "career_wins": 187,
      "career_losses": 83,
      "prize_money": "$11,956,334",
      "highest_ranking": 3,
      "year_turned_pro": 2018
    },
    {
      "id": 4,
      "name": "Elena Rybakina",
      "nationality": "Kazakhstan",
      "age": 25,
      "ranking": 4,
      "racquet": "Yonex VCORE 97",
      "plays": "Right-handed (two-handed backhand)",
      "coach": "Stefano Vukov",
      "career_titles": 7,
      "grand_slam_titles": 1,
      "career_wins": 227,
      "career_losses": 115,
      "prize_money": "$12,304,655",
      "highest_ranking": 3,
      "year_turned_pro": 2016
    },
    {
      "id": 5,
      "name": "Jessica Pegula",
      "nationality": "United States",
      "age": 30,
      "ranking": 5,
      "racquet": "Yonex EZONE 98",
      "plays": "Right-handed (two-handed backhand)",
      "coach": "David Witt",
      "career_titles": 4,
      "grand_slam_titles": 0,
      "career_wins": 264,
      "career_losses": 169,
      "prize_money": "$11,862,413",
      "highest_ranking": 3,
      "year_turned_pro": 2009
    }
  ]
}
